print_loader/__about__.py
print_loader/__init__.py
print_loader-0.0.1a4.dist-info/METADATA
print_loader-0.0.1a4.dist-info/WHEEL
print_loader-0.0.1a4.dist-info/licenses/LICENSE.txt
print_loader-0.0.1a4.dist-info/RECORD
