Metadata-Version: 2.1
Name: print-loader
Version: 0.0.1a4
Summary: Print a message with an indefinite loader
Project-URL: Issues, https://github.com/NooraHealth/print-loader/issues
Project-URL: Source, https://github.com/NooraHealth/print-loader
Author-email: abhishek-compro <abhishek.prasad@noorahealth.org>
Maintainer-email: abhishek-compro <abhishek.prasad@noorahealth.org>
License-File: LICENSE.txt
Keywords: aesthetic,ansi escape sequence,attractive,block of code,clear line,code block,console,context manager,continuous,custom,design,load,loader,loading,prettify,pretty,print,putty,same line,terminal,with
Classifier: Development Status :: 1 - Planning
Classifier: Environment :: Console
Classifier: Operating System :: POSIX
Classifier: Programming Language :: Python
Classifier: Programming Language :: Python :: 3.10
Classifier: Programming Language :: Python :: 3.11
Classifier: Programming Language :: Python :: Implementation :: PyPy
Classifier: Topic :: Artistic Software
Requires-Python: >=3.10
